Workbook

Sheet Панель
A1: RPO та RTO: відновлення після ransomware-інциденту
A2: Сценарій: ransomware-атака на інтернет-магазин. Зашифровано сервер сайту, базу замовлень, частину CRM та файлове сховище. Мета — мінімізувати втрату даних і час простою.
A5: Систем у плані | C5: Висока критичність | E5: Мін. RPO | G5: Мін. RTO
A6: =COUNTA(RPO!A4:A10) -> 7 | C6: =COUNTIF(RPO!B4:B10,"Висока") -> 3 | E6: =MIN(RPO!E4:E10)&" хв" -> 5 хв | G6: =MIN(RTO!E4:E10)&" хв" -> 30 хв
A9: Зведена таблиця для контролю пріоритетів
A10: Система | B10: Критичність | C10: RPO, хв | D10: RTO, хв | E10: RPO, формат | F10: RTO, формат | G10: Пріоритет | H10: Коментар
A11: =RPO!A4 -> Сайт інтернет-магазину | B11: =RPO!B4 -> Висока | C11: =RPO!E4 -> 15 | D11: =RTO!E4 -> 30 | E11: =IF(C11<60,C11&" хв",ROUND(C11/60,1)&" год") -> 15 хв | F11: =IF(D11<60,D11&" хв",ROUND(D11/60,1)&" год") -> 30 хв | G11: =IF(OR(B11="Висока",D11<=60),"1 — відновлювати першою",IF(D11<=240,"2 — після критичних систем","3 — планове відновлення")) -> 1 — відновлювати першою | H11: =IF(D11>240,"Можна відновлювати пізніше",IF(C11<=30,"Потрібна часта синхронізація","Потрібен контроль backup")) -> Потрібна часта синхронізація
A12: =RPO!A5 -> База замовлень | B12: =RPO!B5 -> Висока | C12: =RPO!E5 -> 5 | D12: =RTO!E5 -> 60 | E12: =IF(C12<60,C12&" хв",ROUND(C12/60,1)&" год") -> 5 хв | F12: =IF(D12<60,D12&" хв",ROUND(D12/60,1)&" год") -> 1 год | G12: =IF(OR(B12="Висока",D12<=60),"1 — відновлювати першою",IF(D12<=240,"2 — після критичних систем","3 — планове відновлення")) -> 1 — відновлювати першою | H12: =IF(D12>240,"Можна відновлювати пізніше",IF(C12<=30,"Потрібна часта синхронізація","Потрібен контроль backup")) -> Потрібна часта синхронізація
A13: =RPO!A6 -> Платіжна інтеграція | B13: =RPO!B6 -> Висока | C13: =RPO!E6 -> 5 | D13: =RTO!E6 -> 60 | E13: =IF(C13<60,C13&" хв",ROUND(C13/60,1)&" год") -> 5 хв | F13: =IF(D13<60,D13&" хв",ROUND(D13/60,1)&" год") -> 1 год | G13: =IF(OR(B13="Висока",D13<=60),"1 — відновлювати першою",IF(D13<=240,"2 — після критичних систем","3 — планове відновлення")) -> 1 — відновлювати першою | H13: =IF(D13>240,"Можна відновлювати пізніше",IF(C13<=30,"Потрібна часта синхронізація","Потрібен контроль backup")) -> Потрібна часта синхронізація
A14: =RPO!A7 -> Складський облік | B14: =RPO!B7 -> Середня | C14: =RPO!E7 -> 30 | D14: =RTO!E7 -> 180 | E14: =IF(C14<60,C14&" хв",ROUND(C14/60,1)&" год") -> 30 хв | F14: =IF(D14<60,D14&" хв",ROUND(D14/60,1)&" год") -> 3 год | G14: =IF(OR(B14="Висока",D14<=60),"1 — відновлювати першою",IF(D14<=240,"2 — після критичних систем","3 — планове відновлення")) -> 2 — після критичних систем | H14: =IF(D14>240,"Можна відновлювати пізніше",IF(C14<=30,"Потрібна часта синхронізація","Потрібен контроль backup")) -> Потрібна часта синхронізація
A15: =RPO!A8 -> CRM та підтримка клієнтів | B15: =RPO!B8 -> Середня | C15: =RPO!E8 -> 60 | D15: =RTO!E8 -> 240 | E15: =IF(C15<60,C15&" хв",ROUND(C15/60,1)&" год") -> 1 год | F15: =IF(D15<60,D15&" хв",ROUND(D15/60,1)&" год") -> 4 год | G15: =IF(OR(B15="Висока",D15<=60),"1 — відновлювати першою",IF(D15<=240,"2 — після критичних систем","3 — планове відновлення")) -> 2 — після критичних систем | H15: =IF(D15>240,"Можна відновлювати пізніше",IF(C15<=30,"Потрібна часта синхронізація","Потрібен контроль backup")) -> Потрібен контроль backup
A16: =RPO!A9 -> Файлове сховище документів | B16: =RPO!B9 -> Низька/середня | C16: =RPO!E9 -> 720 | D16: =RTO!E9 -> 480 | E16: =IF(C16<60,C16&" хв",ROUND(C16/60,1)&" год") -> 12 год | F16: =IF(D16<60,D16&" хв",ROUND(D16/60,1)&" год") -> 8 год | G16: =IF(OR(B16="Висока",D16<=60),"1 — відновлювати першою",IF(D16<=240,"2 — після критичних систем","3 — планове відновлення")) -> 3 — планове відновлення | H16: =IF(D16>240,"Можна відновлювати пізніше",IF(C16<=30,"Потрібна часта синхронізація","Потрібен контроль backup")) -> Можна відновлювати пізніше
A17: =RPO!A10 -> Логи безпеки та системні журнали | B17: =RPO!B10 -> Середня | C17: =RPO!E10 -> 1440 | D17: =RTO!E10 -> 720 | E17: =IF(C17<60,C17&" хв",ROUND(C17/60,1)&" год") -> 24 год | F17: =IF(D17<60,D17&" хв",ROUND(D17/60,1)&" год") -> 12 год | G17: =IF(OR(B17="Висока",D17<=60),"1 — відновлювати першою",IF(D17<=240,"2 — після критичних систем","3 — планове відновлення")) -> 3 — планове відновлення | H17: =IF(D17>240,"Можна відновлювати пізніше",IF(C17<=30,"Потрібна часта синхронізація","Потрібен контроль backup")) -> Можна відновлювати пізніше
A18: Ключовий висновок: першими відновлюються сайт, база замовлень і платежі; для них потрібні найменші RPO/RTO та автоматизовані резервні рішення.

Sheet RPO
A1: 1. Допустимий RPO для різних систем
A3: Система | B3: Критичність | C3: Інтервал backup, хв | D3: Затримка реплікації, хв | E3: RPO, хв | F3: RPO, формат | G3: Що це означає? | H3: Як забезпечити
A4: Сайт інтернет-магазину | B4: Висока | C4: 15 | D4: 0 | E4: =C4+D4 -> 15 | F4: =IF(E4<60,E4&" хв",ROUND(E4/60,1)&" год") -> 15 хв | G4: Сайт має використовувати актуальну версію каталогу, кошика та сесій клієнтів. | H4: CDN + резервний вебсервер + копія конфігурації кожні 15 хвилин
A5: База замовлень | B5: Висока | C5: 5 | D5: 0 | E5: =C5+D5 -> 5 | F5: =IF(E5<60,E5&" хв",ROUND(E5/60,1)&" год") -> 5 хв | G5: Компанія може втратити максимум 5 хвилин нових замовлень. | H5: Реплікація майже в реальному часі + backup кожні 5 хвилин
A6: Платіжна інтеграція | B6: Висока | C6: 5 | D6: 0 | E6: =C6+D6 -> 5 | F6: =IF(E6<60,E6&" хв",ROUND(E6/60,1)&" год") -> 5 хв | G6: Втрата платіжних транзакцій неприпустима або має бути мінімальною. | H6: Зовнішній платіжний провайдер + журналювання транзакцій
A7: Складський облік | B7: Середня | C7: 30 | D7: 0 | E7: =C7+D7 -> 30 | F7: =IF(E7<60,E7&" хв",ROUND(E7/60,1)&" год") -> 30 хв | G7: Можлива незначна неточність у залишках товарів, яку можна звірити після відновлення. | H7: Інкрементальний backup кожні 30 хвилин
A8: CRM та підтримка клієнтів | B8: Середня | C8: 60 | D8: 0 | E8: =C8+D8 -> 60 | F8: =IF(E8<60,E8&" хв",ROUND(E8/60,1)&" год") -> 1 год | G8: Втрата частини звернень клієнтів за останню годину небажана, але не блокує продажі повністю. | H8: Погодинне резервне копіювання + хмарна копія
A9: Файлове сховище документів | B9: Низька/середня | C9: 720 | D9: 0 | E9: =C9+D9 -> 720 | F9: =IF(E9<60,E9&" хв",ROUND(E9/60,1)&" год") -> 12 год | G9: Документи змінюються нечасто, тому допустима втрата останніх змін за пів дня. | H9: Резервне копіювання 2 рази на день
A10: Логи безпеки та системні журнали | B10: Середня | C10: 1440 | D10: 0 | E10: =C10+D10 -> 1440 | F10: =IF(E10<60,E10&" хв",ROUND(E10/60,1)&" год") -> 24 год | G10: Частина логів може бути втрачена, але бажано зберегти їх для розслідування. | H10: Щоденне архівування + передача логів у SIEM

Sheet RTO
A1: 2. Допустимий RTO для різних систем
A3: Система | B3: Критичність | C3: Час запуску резерву, хв | D3: Час перевірки, хв | E3: RTO, хв | F3: RTO, формат | G3: Що це означає? | H3: Резервне рішення
A4: Сайт інтернет-магазину | B4: Висока | C4: 20 | D4: 10 | E4: =C4+D4 -> 30 | F4: =IF(E4<60,E4&" хв",ROUND(E4/60,1)&" год") -> 30 хв | G4: Сайт має бути доступний клієнтам максимум через 30 хвилин після інциденту. | H4: Резервний вебсервер або хмарне середовище
A5: База замовлень | B5: Висока | C5: 40 | D5: 20 | E5: =C5+D5 -> 60 | F5: =IF(E5<60,E5&" хв",ROUND(E5/60,1)&" год") -> 1 год | G5: Замовлення мають бути відновлені максимум за 1 годину, інакше бізнес втрачатиме продажі. | H5: Реплікація бази даних + автоматизоване відновлення
A6: Платіжна інтеграція | B6: Висока | C6: 45 | D6: 15 | E6: =C6+D6 -> 60 | F6: =IF(E6<60,E6&" хв",ROUND(E6/60,1)&" год") -> 1 год | G6: Клієнти повинні знову мати можливість оплачувати замовлення протягом 1 години. | H6: Резервний канал інтеграції або fallback-провайдер
A7: Складський облік | B7: Середня | C7: 120 | D7: 60 | E7: =C7+D7 -> 180 | F7: =IF(E7<60,E7&" хв",ROUND(E7/60,1)&" год") -> 3 год | G7: Працівники складу можуть тимчасово працювати вручну, але не довше 3 годин. | H7: Резервна копія бази та окремий сервер
A8: CRM та підтримка клієнтів | B8: Середня | C8: 180 | D8: 60 | E8: =C8+D8 -> 240 | F8: =IF(E8<60,E8&" хв",ROUND(E8/60,1)&" год") -> 4 год | G8: Підтримка може працювати з обмеженнями, але тривалий простій погіршить сервіс. | H8: Хмарне резервування CRM
A9: Файлове сховище документів | B9: Низька/середня | C9: 360 | D9: 120 | E9: =C9+D9 -> 480 | F9: =IF(E9<60,E9&" хв",ROUND(E9/60,1)&" год") -> 8 год | G9: Документи не є критичними для миттєвого продажу, тому можуть бути відновлені пізніше. | H9: Стандартне резервне копіювання + архівне сховище
A10: Логи безпеки та системні журнали | B10: Середня | C10: 480 | D10: 240 | E10: =C10+D10 -> 720 | F10: =IF(E10<60,E10&" хв",ROUND(E10/60,1)&" год") -> 12 год | G10: Логи важливі для аналізу атаки, але не обов’язково відновлювати їх першими. | H10: Централізований збір логів і архів

Sheet Заходи
A1: 3. Заходи для забезпечення RPO та RTO
A3: Захід відновлення | B3: Що захищає? | C3: Для яких систем? | D3: Як забезпечує RPO/RTO? | E3: Чому це важливо? | F3: Пріоритет
A4: Реплікація бази даних у реальному часі | B4: Замовлення, платежі, клієнтські дані | C4: База замовлень, платіжна інтеграція, CRM | D4: RPO 0–5 хвилин | E4: Мінімізує втрату критичних бізнес-даних | F4: Висока
A5: Автоматичне перемикання на резервний сервер | B5: Доступність сайту та бази даних | C5: Сайт, база замовлень | D5: RTO 30–60 хвилин | E5: Зменшує час простою після атаки | F5: Висока
A6: Інкрементальні резервні копії | B6: Зміни в базах даних і файлах | C6: CRM, складський облік, файлове сховище | D6: RPO 30–720 хвилин | E6: Зберігає часті зміни без великого навантаження | F6: Середня
A7: Immutable backups — незмінювані резервні копії | B7: Захист резервних копій від шифрування | C7: Усі критичні системи | D7: Підтримує RPO/RTO після ransomware | E7: Зловмисники не зможуть змінити або видалити копії | F7: Висока
A8: Окреме хмарне резервне середовище | B8: Роботу бізнесу після повного збою основної інфраструктури | C8: Сайт, база замовлень, CRM | D8: Прискорює RTO | E8: Потрібне, якщо основний сервер повністю недоступний | F8: Висока
A9: Централізований збір логів | B9: Дані для розслідування інциденту | C9: Логи безпеки, системні журнали | D9: Зменшує ризик втрати доказів | E9: Допомагає зрозуміти джерело та масштаб атаки | F9: Середня
A10: Регулярне тестування відновлення | B10: Перевірку працездатності резервних копій | C10: Усі системи | D10: Підтверджує реальність RPO/RTO | E10: Без тестування резервні копії можуть бути непридатними | F10: Висока

Sheet Розрахунки
A1: Формули та розрахунки для Google Sheets
A3: Змінюйте вхідні значення у стовпцях C:D на аркушах RPO та RTO — результати перерахуються автоматично.
A5: Показник | B5: Формула | C5: Де використовується | D5: Пояснення | E5: Приклад системи | F5: Результат, хв | G5: Результат, формат
A6: RPO | B6: =Інтервал backup + Затримка реплікації | C6: RPO!E4:E10 | D6: Скільки даних можна втратити після інциденту. | E6: База замовлень | F6: =RPO!E5 -> 5 | G6: =RPO!F5 -> 5 хв
A7: RTO | B7: =Час запуску резерву + Час перевірки | C7: RTO!E4:E10 | D7: За який максимальний час система має бути відновлена. | E7: База замовлень | F7: =RTO!E5 -> 60 | G7: =RTO!F5 -> 1 год
A8: Пріоритет | B8: =IF(критичність або RTO<=60 хв, пріоритет 1, ...) | C8: Панель!G11:G17 | D8: Визначає порядок відновлення систем. | E8: Сайт | F8: =RTO!E4 -> 30 | G8: =RTO!F4 -> 30 хв

Sheet ДЗ9_Панель
A1: ДЗ9: Переоцінка ризиків після заходів контролю
A2: Сценарій: ransomware-атака на інтернет-магазин. Показники нижче автоматично підтягуються з аркуша ДЗ9_FAIR.
A4: Показник | B4: Значення | D4: Рішення | E4: Значення | F4: Коментар
A5: ALE до контролів | B5: =ДЗ9_FAIR!H12 -> 199650 | D5: Сукупний RR | E5: =ДЗ9_FAIR!S12 -> 28755.037 | F5: Має бути нижче прийнятного порогу
A6: RR після контролів | B6: =ДЗ9_FAIR!S12 -> 28755.037 | D6: Прийнятний поріг | E6: =ДЗ9_FAIR!D3 -> 50000 | F6: Поріг можна змінити на ДЗ9_FAIR!D3
A7: Зменшення очікуваних втрат | B7: =ДЗ9_FAIR!T12 -> 170894.96 | D7: Кількість прийнятних систем | E7: =COUNTIF(ДЗ9_FAIR!W5:W11,"Прийнятний")&" із "&COUNTA(ДЗ9_FAIR!A5:A11) -> 7 із 7 | F7: Статус формується автоматично
A8: Ефективність контролів CF | B8: =ДЗ9_FAIR!R12 -> 0.85597276 | D8: Загальний висновок | E8: =IF(E5<=E6,"Прийнятний","Потребує додаткових заходів") -> Прийнятний | F8: Остаточна стратегія: мінімізація + передача + прийняття
A9: Вартість контролів/рік | B9: =ДЗ9_FAIR!Y12 -> 59500 | D9: Економічна доцільність | E9: =IF(ДЗ9_FAIR!Z12>0,"Доцільно","Потрібно переглянути") -> Доцільно | F9: Порівнюється вигода від зменшення ALE з річною вартістю контролів
A11: Система | B11: ALE до, $ | C11: RR після, $
A12: Сайт інтернет-магазину | B12: =ДЗ9_FAIR!H5 -> 49500 | C12: =ДЗ9_FAIR!S5 -> 5240.8125
A13: База замовлень | B13: =ДЗ9_FAIR!H6 -> 72000 | C13: =ДЗ9_FAIR!S6 -> 6318
A14: Платіжна інтеграція | B14: =ДЗ9_FAIR!H7 -> 39000 | C14: =ДЗ9_FAIR!S7 -> 5460
A15: Складський облік | B15: =ДЗ9_FAIR!H8 -> 12000 | C15: =ДЗ9_FAIR!S8 -> 3712.5
A16: CRM та підтримка клієнтів | B16: =ДЗ9_FAIR!H9 -> 15750 | C16: =ДЗ9_FAIR!S9 -> 4134.375
A17: Файлове сховище документів | B17: =ДЗ9_FAIR!H10 -> 7200 | C17: =ДЗ9_FAIR!S10 -> 2764.8
A18: Логи безпеки та системні журнали | B18: =ДЗ9_FAIR!H11 -> 4200 | C18: =ДЗ9_FAIR!S11 -> 1124.55
A20: Фінальний висновок для LMS
A21: Після контролів очікувані фінансові втрати зменшуються з ALE до залишкового ризику RR. Оскільки RR нижчий за встановлений прийнятний рівень, компанія може прийняти частину ризику, але для критичних систем залишає стратегію мінімізації та передачі ризику.
A22: Обрані стратегії: мінімізація для сайту, бази замовлень, CRM і логів; передача для платіжної інтеграції та частини фінансових наслідків через кіберстрахування; прийняття для нижчих залишкових ризиків після контролів.
A23: Подальші дії: регулярне тестування відновлення, контроль RPO/RTO, перевірка immutable backups, оновлення правил EDR/SIEM та щорічний перегляд фінансових параметрів ризику.

Sheet ДЗ9_FAIR
A1: ДЗ9. Переоцінка ризиків та вибір стратегії керування
A2: Кейс: ransomware-атака на інтернет-магазин. Модель показує зміну параметрів FAIR після контролів, розрахунок RR = ALE × (1 − CF), фінансовий ефект і стратегію керування залишковим ризиком.
A3: Прийнятний рівень ризику на систему, $ | B3: 10000 | C3: Прийнятний сукупний RR, $ | D3: 50000 | E3: Усі жовті клітинки можна редагувати
A4: Система | B4: Критичність | C4: Сценарій ризику | D4: Loss Magnitude до, $ | E4: TEF до | F4: Vuln до | G4: LEF до | H4: ALE до, $ | I4: Впроваджені контролі | J4: Зменшення TEF | K4: Зменшення Vuln | L4: Зменшення Loss | M4: TEF після | N4: Vuln після | O4: LEF після | P4: Loss Magnitude після, $ | Q4: ALE після, $ | R4: CF | S4: RR = ALE×(1−CF), $ | T4: Зменшення втрат, $ | U4: Зменшення, % | V4: Стратегія | W4: Статус прийнятності | X4: Обґрунтування | Y4: Вартість контролів/рік, $ | Z4: Чистий ефект, $ | AA4: ROI | AB4: Рішення | AC4: Додаткові дії
A5: Сайт інтернет-магазину | B5: Висока | C5: Шифрування вебсервера, простій продажів і кошика | D5: 45000 | E5: 2 | F5: 0.55 | G5: =E5*F5 -> 1.1 | H5: =D5*G5 -> 49500 | I5: EDR, hardening, WAF/CDN, резервний вебсервер, регулярні restore-тести | J5: 0.45 | K5: 0.65 | L5: 0.45 | M5: =E5*(1-J5) -> 1.1 | N5: =F5*(1-K5) -> 0.1925 | O5: =M5*N5 -> 0.21175 | P5: =D5*(1-L5) -> 24750 | Q5: =O5*P5 -> 5240.8125 | R5: =IFERROR(1-(Q5/H5),0) -> 0.894125 | S5: =H5*(1-R5) -> 5240.8125 | T5: =H5-S5 -> 44259.188 | U5: =IFERROR(T5/H5,0) -> 0.894125 | V5: Мінімізація + прийняття | W5: =IF(S5<=$B$3,"Прийнятний","Потребує додаткових дій") -> Прийнятний | X5: Після контролів RR нижчий за поріг; критичність висока, тому ризик не лише приймається, а й постійно мінімізується. | Y5: 12000 | Z5: =T5-Y5 -> 32259.188 | AA5: =IFERROR(Z5/Y5,0) -> 2.6882656 | AB5: =IF(Z5>0,"Економічно доцільно","Переглянути бюджет контролів") -> Економічно доцільно | AC5: Щоквартальний тест failover і контроль RTO 30 хв.
A6: База замовлень | B6: Висока | C6: Шифрування/втрата нових замовлень і історії покупок | D6: 80000 | E6: 1.5 | F6: 0.6 | G6: =E6*F6 -> 0.9 | H6: =D6*G6 -> 72000 | I6: Реплікація БД, immutable backups, MFA для адміністраторів, сегментація | J6: 0.35 | K6: 0.7 | L6: 0.55 | M6: =E6*(1-J6) -> 0.975 | N6: =F6*(1-K6) -> 0.18 | O6: =M6*N6 -> 0.1755 | P6: =D6*(1-L6) -> 36000 | Q6: =O6*P6 -> 6318 | R6: =IFERROR(1-(Q6/H6),0) -> 0.91225 | S6: =H6*(1-R6) -> 6318 | T6: =H6-S6 -> 65682 | U6: =IFERROR(T6/H6,0) -> 0.91225 | V6: Мінімізація + передача | W6: =IF(S6<=$B$3,"Прийнятний","Потребує додаткових дій") -> Прийнятний | X6: Найбільш критична бізнес-система; залишковий ризик знижений, але частину фінансового впливу доцільно передати через кіберстрахування. | Y6: 18000 | Z6: =T6-Y6 -> 47682 | AA6: =IFERROR(Z6/Y6,0) -> 2.649 | AB6: =IF(Z6>0,"Економічно доцільно","Переглянути бюджет контролів") -> Економічно доцільно | AC6: Додати моніторинг аномальних масових змін у БД.
A7: Платіжна інтеграція | B7: Висока | C7: Неможливість приймати оплату або розбіжності в транзакціях | D7: 65000 | E7: 1.2 | F7: 0.5 | G7: =E7*F7 -> 0.6 | H7: =D7*G7 -> 39000 | I7: Зовнішній платіжний провайдер, журналювання транзакцій, резервний канал оплати | J7: 0.3 | K7: 0.6 | L7: 0.5 | M7: =E7*(1-J7) -> 0.84 | N7: =F7*(1-K7) -> 0.2 | O7: =M7*N7 -> 0.168 | P7: =D7*(1-L7) -> 32500 | Q7: =O7*P7 -> 5460 | R7: =IFERROR(1-(Q7/H7),0) -> 0.86 | S7: =H7*(1-R7) -> 5460 | T7: =H7-S7 -> 33540 | U7: =IFERROR(T7/H7,0) -> 0.86 | V7: Передача + мінімізація | W7: =IF(S7<=$B$3,"Прийнятний","Потребує додаткових дій") -> Прийнятний | X7: Основну частину операційного ризику передано провайдеру; внутрішні журнали й fallback зменшують залишкові втрати. | Y7: 8000 | Z7: =T7-Y7 -> 25540 | AA7: =IFERROR(Z7/Y7,0) -> 3.1925 | AB7: =IF(Z7>0,"Економічно доцільно","Переглянути бюджет контролів") -> Економічно доцільно | AC7: Перевіряти SLA провайдера та сценарій fallback-оплати.
A8: Складський облік | B8: Середня | C8: Неточні залишки товарів після відновлення | D8: 30000 | E8: 1 | F8: 0.4 | G8: =E8*F8 -> 0.4 | H8: =D8*G8 -> 12000 | I8: Інкрементальні backup, ручний аварійний процес, звірка залишків | J8: 0.25 | K8: 0.45 | L8: 0.25 | M8: =E8*(1-J8) -> 0.75 | N8: =F8*(1-K8) -> 0.22 | O8: =M8*N8 -> 0.165 | P8: =D8*(1-L8) -> 22500 | Q8: =O8*P8 -> 3712.5 | R8: =IFERROR(1-(Q8/H8),0) -> 0.690625 | S8: =H8*(1-R8) -> 3712.5 | T8: =H8-S8 -> 8287.5 | U8: =IFERROR(T8/H8,0) -> 0.690625 | V8: Мінімізація + прийняття | W8: =IF(S8<=$B$3,"Прийнятний","Потребує додаткових дій") -> Прийнятний | X8: Ризик прийнятний, бо тимчасовий ручний процес дозволяє не зупиняти продажі повністю. | Y8: 5000 | Z8: =T8-Y8 -> 3287.5 | AA8: =IFERROR(Z8/Y8,0) -> 0.6575 | AB8: =IF(Z8>0,"Економічно доцільно","Переглянути бюджет контролів") -> Економічно доцільно | AC8: Провести тренування складу для ручного режиму раз на пів року.
A9: CRM та підтримка клієнтів | B9: Середня | C9: Втрата звернень клієнтів і історії комунікацій | D9: 35000 | E9: 1 | F9: 0.45 | G9: =E9*F9 -> 0.45 | H9: =D9*G9 -> 15750 | I9: Хмарний backup CRM, MFA, контроль прав доступу, шаблони кризової комунікації | J9: 0.25 | K9: 0.5 | L9: 0.3 | M9: =E9*(1-J9) -> 0.75 | N9: =F9*(1-K9) -> 0.225 | O9: =M9*N9 -> 0.16875 | P9: =D9*(1-L9) -> 24500 | Q9: =O9*P9 -> 4134.375 | R9: =IFERROR(1-(Q9/H9),0) -> 0.7375 | S9: =H9*(1-R9) -> 4134.375 | T9: =H9-S9 -> 11615.625 | U9: =IFERROR(T9/H9,0) -> 0.7375 | V9: Мінімізація + прийняття | W9: =IF(S9<=$B$3,"Прийнятний","Потребує додаткових дій") -> Прийнятний | X9: Залишковий ризик нижчий за поріг; додатково підтримка може працювати за резервним комунікаційним процесом. | Y9: 6000 | Z9: =T9-Y9 -> 5615.625 | AA9: =IFERROR(Z9/Y9,0) -> 0.9359375 | AB9: =IF(Z9>0,"Економічно доцільно","Переглянути бюджет контролів") -> Економічно доцільно | AC9: Оновлювати експорт клієнтських даних і сценарії сповіщення.
A10: Файлове сховище документів | B10: Низька/середня | C10: Шифрування внутрішніх документів | D10: 20000 | E10: 0.8 | F10: 0.45 | G10: =E10*F10 -> 0.36 | H10: =D10*G10 -> 7200 | I10: Щоденний backup, immutable storage, розмежування прав на файлові папки | J10: 0.2 | K10: 0.4 | L10: 0.2 | M10: =E10*(1-J10) -> 0.64 | N10: =F10*(1-K10) -> 0.27 | O10: =M10*N10 -> 0.1728 | P10: =D10*(1-L10) -> 16000 | Q10: =O10*P10 -> 2764.8 | R10: =IFERROR(1-(Q10/H10),0) -> 0.616 | S10: =H10*(1-R10) -> 2764.8 | T10: =H10-S10 -> 4435.2 | U10: =IFERROR(T10/H10,0) -> 0.616 | V10: Прийняття + мінімізація | W10: =IF(S10<=$B$3,"Прийнятний","Потребує додаткових дій") -> Прийнятний | X10: Система не зупиняє основний продаж; після стандартних резервних копій залишковий ризик можна прийняти. | Y10: 4000 | Z10: =T10-Y10 -> 435.2 | AA10: =IFERROR(Z10/Y10,0) -> 0.1088 | AB10: =IF(Z10>0,"Економічно доцільно","Переглянути бюджет контролів") -> Економічно доцільно | AC10: Контролювати, щоб backup не був доступний із доменних облікових записів.
A11: Логи безпеки та системні журнали | B11: Середня | C11: Втрата доказів інциденту й ускладнення розслідування | D11: 15000 | E11: 0.8 | F11: 0.35 | G11: =E11*F11 -> 0.28 | H11: =D11*G11 -> 4200 | I11: SIEM, централізований збір логів, write-once архів, обмеження доступу | J11: 0.3 | K11: 0.55 | L11: 0.15 | M11: =E11*(1-J11) -> 0.56 | N11: =F11*(1-K11) -> 0.1575 | O11: =M11*N11 -> 0.0882 | P11: =D11*(1-L11) -> 12750 | Q11: =O11*P11 -> 1124.55 | R11: =IFERROR(1-(Q11/H11),0) -> 0.73225 | S11: =H11*(1-R11) -> 1124.55 | T11: =H11-S11 -> 3075.45 | U11: =IFERROR(T11/H11,0) -> 0.73225 | V11: Мінімізація | W11: =IF(S11<=$B$3,"Прийнятний","Потребує додаткових дій") -> Прийнятний | X11: Логи важливі для форензіки; навіть при невисоких прямих втратах ризик потрібно мінімізувати. | Y11: 6500 | Z11: =T11-Y11 -> -3424.55 | AA11: =IFERROR(Z11/Y11,0) -> -0.52685385 | AB11: =IF(Z11>0,"Економічно доцільно","Переглянути бюджет контролів") -> Переглянути бюджет контролів | AC11: Зберігати ключові логи окремо від основного домену.
A12: Разом / середнє | D12: =SUM(D5:D11) -> 290000 | E12: =AVERAGE(E5:E11) -> 1.1857143 | F12: =AVERAGE(F5:F11) -> 0.47142857 | G12: =SUM(G5:G11) -> 4.09 | H12: =SUM(H5:H11) -> 199650 | J12: =AVERAGE(J5:J11) -> 0.3 | K12: =AVERAGE(K5:K11) -> 0.55 | L12: =AVERAGE(L5:L11) -> 0.34285714 | M12: =AVERAGE(M5:M11) -> 0.80214286 | N12: =AVERAGE(N5:N11) -> 0.20642857 | O12: =SUM(O5:O11) -> 1.15 | P12: =SUM(P5:P11) -> 169000 | Q12: =SUM(Q5:Q11) -> 28755.037 | R12: =IFERROR(1-(Q12/H12),0) -> 0.85597276 | S12: =SUM(S5:S11) -> 28755.037 | T12: =SUM(T5:T11) -> 170894.96 | U12: =IFERROR(T12/H12,0) -> 0.85597276 | Y12: =SUM(Y5:Y11) -> 59500 | Z12: =SUM(Z5:Z11) -> 111394.96 | AA12: =IFERROR(Z12/Y12,0) -> 1.8721842

Sheet ДЗ9_Стратегії
A1: Вибір стратегії керування залишковим ризиком
A2: Стратегія | B2: Коли застосовується | C2: Як впливає на RR | D2: Приклад у цьому кейсі | E2: Фінансова логіка | F2: Ризик після стратегії | G2: Контрольний власник | H2: Періодичність перегляду
A3: Прийняття ризику | B3: RR нижчий за прийнятний поріг і не блокує основний бізнес-процес. | C3: RR залишається, але компанія усвідомлено його покриває. | D3: Файлове сховище після immutable backups і регулярних копій. | E3: Вартість додаткового зниження може бути більшою, ніж очікувана вигода. | F3: Низький/керований | G3: CISO + власник процесу | H3: Щороку або після інциденту
A4: Мінімізація ризику | B4: Система критична або RR все ще має операційний вплив. | C4: Зменшує TEF, Vuln і/або Loss Magnitude. | D4: Сайт, база замовлень, CRM, SIEM/логи. | E4: Доцільно, якщо очікуване зменшення ALE перевищує витрати контролів. | F4: Знижений, але не нульовий | G4: IT Security + Infrastructure | H4: Щоквартально
A5: Передача ризику | B5: Фінансові наслідки можна передати третій стороні або покрити страховкою. | C5: Не усуває подію, але зменшує прямий фінансовий вплив компанії. | D5: Платіжний провайдер, кіберстрахування для бази замовлень. | E5: Платіжний SLA/страхування зменшують Loss Magnitude. | F5: Частково переданий | G5: Legal + Finance + CISO | H5: Щороку при оновленні договорів
A6: Уникнення ризику | B6: Процес має неприйнятний RR і його можна замінити/закрити. | C6: Ризик усувається через відмову від небезпечної активності. | D6: Не обрано як основну стратегію, бо інтернет-магазин не може відмовитись від продажів онлайн. | E6: Застосовується лише якщо очікувані втрати перевищують бізнес-цінність процесу. | F6: Мінімальний або відсутній | G6: Executive Management | H6: За потреби

Sheet ДЗ9_Висновок
A1: Пояснення, формули та фінальний висновок
A3: Показник | B3: Формула | C3: Джерело в таблиці | D3: Пояснення
A4: LEF до | B4: TEF до × Vuln до | C4: ДЗ9_FAIR!G5:G12 | D4: Очікувана частота подій втрат до впровадження контролів.
A5: ALE до | B5: Loss Magnitude до × LEF до | C5: ДЗ9_FAIR!H5:H12 | D5: Очікувані річні фінансові втрати до контролів.
A6: TEF після | B6: TEF до × (1 − зменшення TEF) | C6: ДЗ9_FAIR!M5:M12 | D6: Контролі зменшують частоту загрозливих подій.
A7: Vuln після | B7: Vuln до × (1 − зменшення Vuln) | C7: ДЗ9_FAIR!N5:N12 | D7: Контролі зменшують імовірність, що подія стане подією втрат.
A8: ALE після | B8: LEF після × Loss Magnitude після | C8: ДЗ9_FAIR!Q5:Q12 | D8: Переоцінений очікуваний річний збиток після контролів.
A9: CF | B9: 1 − (ALE після / ALE до) | C9: ДЗ9_FAIR!R5:R12 | D9: Загальна ефективність контролів у відсотках.
A10: RR | B10: ALE до × (1 − CF) | C10: ДЗ9_FAIR!S5:S12 | D10: Залишковий ризик після контролів. У цій моделі RR дорівнює переоціненому ALE після контролів.
A11: Чистий ефект | B11: Зменшення втрат − вартість контролів | C11: ДЗ9_FAIR!Z5:Z12 | D11: Показує економічну доцільність заходів контролю.
A12: ROI | B12: Чистий ефект / вартість контролів | C12: ДЗ9_FAIR!AA5:AA12 | D12: Показує віддачу від витрат на кіберзахист.
A14: Фінальний висновок
A15: Після впровадження контролів сукупний ALE зменшується з | B15: =ДЗ9_FAIR!H12 -> 199650 | D15: до | E15: =ДЗ9_FAIR!S12 -> 28755.037 | G15: тобто очікувані втрати знижуються на | H15: =ДЗ9_FAIR!U12 -> 0.85597276
A16: Обраний рівень прийнятного ризику | B16: =ДЗ9_FAIR!D3 -> 50000 | D16: Сукупний RR | E16: =ДЗ9_FAIR!S12 -> 28755.037 | G16: Статус | H16: =IF(E16<=ДЗ9_FAIR!D3,"Прийнятний","Потребує додаткових заходів") -> Прийнятний
A17: Основна стратегія | B17: Для критичних систем використано мінімізацію та передачу ризику; для нижчих залишкових ризиків — прийняття.
A18: Чи потрібно більше змінювати безпеку? | B18: Не потрібно негайно збільшувати бюджет, бо чистий економічний ефект позитивний. Потрібно підтримувати регулярні restore-тести, оновлення EDR/SIEM і перегляд страхового покриття.
A19: Очікувані фінансові втрати після стратегії | B19: =ДЗ9_FAIR!S12 -> 28755.037
A20: Примітка | B20: Усі жовті поля на аркуші ДЗ9_FAIR є припущеннями/вхідними даними. Після зміни значень таблиця перерахує RR, ROI і статус прийнятності.
